dart_mcp/__init__.py
dart_mcp/__main__.py
dart_mcp/gtfs.py
dart_mcp/py.typed
dart_mcp/server.py
dart_mcp/data/dart-tx-us/agency.txt
dart_mcp/data/dart-tx-us/calendar.txt
dart_mcp/data/dart-tx-us/calendar_dates.txt
dart_mcp/data/dart-tx-us/routes.txt
dart_mcp/data/dart-tx-us/shapes.txt
dart_mcp/data/dart-tx-us/stop_times.txt
dart_mcp/data/dart-tx-us/stops.txt
dart_mcp/data/dart-tx-us/trips.txt
dart_mcp-0.1.0.dist-info/METADATA
dart_mcp-0.1.0.dist-info/WHEEL
dart_mcp-0.1.0.dist-info/entry_points.txt
dart_mcp-0.1.0.dist-info/licenses/LICENSE.md
dart_mcp-0.1.0.dist-info/RECORD
