Metadata-Version: 2.4
Name: dart-mcp
Version: 0.1.0
Summary: Model Context Protocol server for DART (Dallas Area Rapid Transit) schedules
Author-email: Sandeep Mehta <sandeep@example.com>
License-File: LICENSE.md
Requires-Python: >=3.9
Requires-Dist: pandas>=2.2.3
